ladybug_comfort/__init__.py
ladybug_comfort/__main__.py
ladybug_comfort/adaptive.py
ladybug_comfort/asv.py
ladybug_comfort/at.py
ladybug_comfort/clo.py
ladybug_comfort/degreetime.py
ladybug_comfort/di.py
ladybug_comfort/hi.py
ladybug_comfort/humidex.py
ladybug_comfort/local.py
ladybug_comfort/pet.py
ladybug_comfort/pmv.py
ladybug_comfort/solarcal.py
ladybug_comfort/ts.py
ladybug_comfort/utci.py
ladybug_comfort/wbgt.py
ladybug_comfort/wc.py
ladybug_comfort/_mannequin/seatedspline.csv
ladybug_comfort/_mannequin/standingspline.csv
ladybug_comfort/chart/__init__.py
ladybug_comfort/chart/adaptive.py
ladybug_comfort/chart/polygonpmv.py
ladybug_comfort/chart/polygonutci.py
ladybug_comfort/cli/__init__.py
ladybug_comfort/cli/_helper.py
ladybug_comfort/cli/datacollection.py
ladybug_comfort/cli/epw.py
ladybug_comfort/cli/map.py
ladybug_comfort/cli/mtx.py
ladybug_comfort/cli/sql.py
ladybug_comfort/collection/__init__.py
ladybug_comfort/collection/adaptive.py
ladybug_comfort/collection/base.py
ladybug_comfort/collection/pet.py
ladybug_comfort/collection/pmv.py
ladybug_comfort/collection/solarcal.py
ladybug_comfort/collection/utci.py
ladybug_comfort/map/__init__.py
ladybug_comfort/map/_enclosure.py
ladybug_comfort/map/_helper.py
ladybug_comfort/map/air.py
ladybug_comfort/map/irr.py
ladybug_comfort/map/mrt.py
ladybug_comfort/map/tcp.py
ladybug_comfort/map/utci.py
ladybug_comfort/parameter/__init__.py
ladybug_comfort/parameter/_base.py
ladybug_comfort/parameter/adaptive.py
ladybug_comfort/parameter/pet.py
ladybug_comfort/parameter/pmv.py
ladybug_comfort/parameter/solarcal.py
ladybug_comfort/parameter/utci.py
ladybug_comfort-0.18.99.dist-info/licenses/LICENSE
ladybug_comfort-0.18.99.dist-info/METADATA
ladybug_comfort-0.18.99.dist-info/WHEEL
ladybug_comfort-0.18.99.dist-info/entry_points.txt
ladybug_comfort-0.18.99.dist-info/top_level.txt
ladybug_comfort-0.18.99.dist-info/RECORD
